MANIFEST.in
README.md
setup.cfg
setup.py
versioneer.py
bin/slurmworm
slurmworm/__init__.py
slurmworm/_version.py
slurmworm/bot.py
slurmworm/imap_monitor.py
slurmworm/package_utils.py
slurmworm.egg-info/PKG-INFO
slurmworm.egg-info/SOURCES.txt
slurmworm.egg-info/dependency_links.txt
slurmworm.egg-info/requires.txt
slurmworm.egg-info/top_level.txt