Metadata-Version: 2.1
Name: slurmworm
Version: 1.0.0
Summary: A simple listener to monitor slurm jobs
Home-page: https://github.com/grburgess/slurmworm
Author: J. Michael Burgess
Author-email: jmichaelburgess@gmail.com
License: UNKNOWN
Project-URL: Bug Tracker, https://github.com/grburgess/slurmworm/issues
Project-URL: Source Code, https://github.com/grburgess/slurmworm
Platform: UNKNOWN
